setup.cfg
setup.py
djcomp/__init__.py
djcomp/admin.py
djcomp/apps.py
djcomp/decorators.py
djcomp/models.py
djcomp/tests.py
djcomp/views.py
djcomp.egg-info/PKG-INFO
djcomp.egg-info/SOURCES.txt
djcomp.egg-info/dependency_links.txt
djcomp.egg-info/top_level.txt
djcomp/migrations/__init__.py
djcomp/templatetags/__init__.py
djcomp/templatetags/djcomp.py
djcomp/templatetags/raw_python.py