Metadata-Version: 1.1
Name: djcomp
Version: 0.0.7
Summary: Django components
Home-page: https://bitbucket.org/hieunv040995/djcomponents
Author: hieunv495
Author-email: hieunv495@gmail.com
License: UNKNOWN
Download-URL: https://bitbucket.org/hieunv040995/djcomponents/get/0.0.1.tar.gz
Keywords: testing,logging,example
Platform: UNKNOWN
